sequencer/__init__.py
sequencer/distance_metrics.py
sequencer/elongation_estimation.py
sequencer/sequencer_.py
TheSequencer-0.0.5.dist-info/LICENSE
TheSequencer-0.0.5.dist-info/METADATA
TheSequencer-0.0.5.dist-info/WHEEL
TheSequencer-0.0.5.dist-info/top_level.txt
TheSequencer-0.0.5.dist-info/RECORD
