Metadata-Version: 2.1
Name: TheSequencer
Version: 0.0.5
Summary: An algorithm that detects one-dimensional sequences in complex datasets
Home-page: https://github.com/dalya/Sequencer
Maintainer: Dalya Baron
Maintainer-email: dalyabaron@gmail.com
License: BSD
Keywords: dimensionality reduction t-sne UMAP
Platform: UNKNOWN
Classifier: Intended Audience :: Science/Research
Classifier: Intended Audience :: Developers
Classifier: License :: OSI Approved :: MIT License
Classifier: Programming Language :: Python :: 3
Classifier: Topic :: Software Development
Classifier: Topic :: Scientific/Engineering
Classifier: Operating System :: Microsoft :: Windows
Classifier: Operating System :: POSIX
Classifier: Operating System :: Unix
Classifier: Operating System :: MacOS
Requires-Python: >=3.6
Requires-Dist: numpy (>=1.13)
Requires-Dist: scikit-learn (>=0.20)
Requires-Dist: scipy (>=1.0)
Requires-Dist: networkx (>=2.4)
Requires-Dist: joblib (>=0.13.2)
